moustovtkwidgets_lib/__init__.py
moustovtkwidgets_lib/mtk_edit_table.py
moustovtkwidgets-0.5.2.dist-info/METADATA
moustovtkwidgets-0.5.2.dist-info/WHEEL
moustovtkwidgets-0.5.2.dist-info/top_level.txt
moustovtkwidgets-0.5.2.dist-info/RECORD
